plotly-scientific-plots/__init__.py
plotly-scientific-plots/misc.py
plotly-scientific-plots/plotly_ML.py
plotly-scientific-plots/plotly_plot_tools.py
plotly_scientific_plots/__init__.py
plotly_scientific_plots/dash_tools.py
plotly_scientific_plots/misc.py
plotly_scientific_plots/misc_computational_tools.py
plotly_scientific_plots/plotly_ML.py
plotly_scientific_plots/plotly_misc.py
plotly_scientific_plots/plotly_plot_tools.py
plotly_scientific_plots-0.1.0.6.dist-info/DESCRIPTION.rst
plotly_scientific_plots-0.1.0.6.dist-info/METADATA
plotly_scientific_plots-0.1.0.6.dist-info/RECORD
plotly_scientific_plots-0.1.0.6.dist-info/WHEEL
plotly_scientific_plots-0.1.0.6.dist-info/metadata.json
plotly_scientific_plots-0.1.0.6.dist-info/top_level.txt
